bfg9000/__init__.py
bfg9000/app_version.py
bfg9000/build.py
bfg9000/build_inputs.py
bfg9000/depfixer.py
bfg9000/driver.py
bfg9000/e1m1.py
bfg9000/environment.py
bfg9000/exceptions.py
bfg9000/file_types.py
bfg9000/glob.py
bfg9000/iterutils.py
bfg9000/jvmoutput.py
bfg9000/languages.py
bfg9000/log.py
bfg9000/objutils.py
bfg9000/options.py
bfg9000/packages.py
bfg9000/path.py
bfg9000/rccdep.py
bfg9000/safe_str.py
bfg9000/versioning.py
bfg9000/arguments/__init__.py
bfg9000/arguments/parser.py
bfg9000/arguments/windows.py
bfg9000/backends/__init__.py
bfg9000/backends/compdb/__init__.py
bfg9000/backends/compdb/writer.py
bfg9000/backends/make/__init__.py
bfg9000/backends/make/syntax.py
bfg9000/backends/make/writer.py
bfg9000/backends/msbuild/__init__.py
bfg9000/backends/msbuild/solution.py
bfg9000/backends/msbuild/syntax.py
bfg9000/backends/msbuild/writer.py
bfg9000/backends/ninja/__init__.py
bfg9000/backends/ninja/syntax.py
bfg9000/backends/ninja/writer.py
bfg9000/builtins/__init__.py
bfg9000/builtins/alias.py
bfg9000/builtins/builtin.py
bfg9000/builtins/clean.py
bfg9000/builtins/command.py
bfg9000/builtins/compile.py
bfg9000/builtins/copy_file.py
bfg9000/builtins/core.py
bfg9000/builtins/default.py
bfg9000/builtins/dist.py
bfg9000/builtins/file_types.py
bfg9000/builtins/find.py
bfg9000/builtins/install.py
bfg9000/builtins/link.py
bfg9000/builtins/opts.py
bfg9000/builtins/packages.py
bfg9000/builtins/path.py
bfg9000/builtins/pkg_config.py
bfg9000/builtins/project.py
bfg9000/builtins/regenerate.py
bfg9000/builtins/tests.py
bfg9000/builtins/toolchain.py
bfg9000/builtins/user_arguments.py
bfg9000/builtins/version.py
bfg9000/platforms/__init__.py
bfg9000/platforms/basepath.py
bfg9000/platforms/core.py
bfg9000/platforms/cygwin.py
bfg9000/platforms/host.py
bfg9000/platforms/posix.py
bfg9000/platforms/target.py
bfg9000/platforms/windows.py
bfg9000/shell/__init__.py
bfg9000/shell/list.py
bfg9000/shell/posix.py
bfg9000/shell/syntax.py
bfg9000/shell/windows.py
bfg9000-0.7.1.dist-info/LICENSE
bfg9000-0.7.1.dist-info/METADATA
bfg9000-0.7.1.dist-info/WHEEL
bfg9000-0.7.1.dist-info/entry_points.txt
bfg9000-0.7.1.dist-info/top_level.txt
bfg9000-0.7.1.dist-info/RECORD
