Metadata-Version: 2.1
Name: bfg9000
Version: 0.7.1
Summary: A cross-platform build file generator
Home-page: https://jimporter.github.io/bfg9000/
Author: Jim Porter
Author-email: itsjimporter@gmail.com
License: BSD-3-Clause
Keywords: build file generator
Platform: UNKNOWN
Classifier: Development Status :: 3 - Alpha
Classifier: Intended Audience :: Developers
Classifier: Topic :: Software Development :: Build Tools
Classifier: License :: OSI Approved :: BSD License
Classifier: Programming Language :: Python :: 3
Classifier: Programming Language :: Python :: 3.6
Classifier: Programming Language :: Python :: 3.7
Classifier: Programming Language :: Python :: 3.8
Classifier: Programming Language :: Python :: 3.9
Classifier: Programming Language :: Python :: 3.10
Classifier: Programming Language :: Python :: 3.11
Requires-Python: >=3.6
Requires-Dist: colorama
Requires-Dist: doppel (>=0.4.0)
Requires-Dist: importlib-metadata
Requires-Dist: importlib-resources
Requires-Dist: mopack (>=0.1.0)
Requires-Dist: pyyaml
Requires-Dist: verspec
Requires-Dist: pysetenv ; platform_system == "Windows"
Provides-Extra: dev
Requires-Dist: coverage ; extra == 'dev'
Requires-Dist: flake8-quotes ; extra == 'dev'
Requires-Dist: flake8 (>=3.7) ; extra == 'dev'
Requires-Dist: lxml ; extra == 'dev'
Requires-Dist: mike (>=0.3.1) ; extra == 'dev'
Requires-Dist: mkdocs-bootswatch-classic ; extra == 'dev'
Requires-Dist: mkdocs-macros-plugin ; extra == 'dev'
Requires-Dist: shtab ; extra == 'dev'
Requires-Dist: stdeb ; extra == 'dev'
Provides-Extra: msbuild
Requires-Dist: lxml ; extra == 'msbuild'
Provides-Extra: test
Requires-Dist: coverage ; extra == 'test'
Requires-Dist: flake8-quotes ; extra == 'test'
Requires-Dist: flake8 (>=3.7) ; extra == 'test'
Requires-Dist: lxml ; extra == 'test'
Requires-Dist: shtab ; extra == 'test'
